Workbook

Sheet Cover
B2: SUBLA TEA
B3: PROJECT EXPENSE TRACKER
B7: Project Name: | C7: Subla Tea — Setup & Build-Out
B8: Location:
B9: Prepared By: | C9: Kazeem Abolaji
B10: Date Prepared:
B11: Reporting Currency: | C11: AED
B12: Project Start Date:
B13: Target Completion Date:
B15: Contents
B16: 1. Instructions — how to use this workbook
B17: 2. Budget Tracker — budget vs. actual by category
B18: 3. Expense Log — every transaction, line by line
B19: 4. Dashboard — visual summary and KPIs
B20: 5. Vendor Directory — supplier/contractor contacts

Sheet Instructions
B2: Company Information
B3: Company Name:
B4: Company Description:
B5: Address Line 1:
B6: Address Line 2:
B7: City:
B8: Emirate/State:
B9: Country:
B10: P.O. Box:
B12: How to Use This Workbook
B14: 1. Set your budget
B15: Go to Budget Tracker and enter the budgeted (planned) amount for each category in the yellow cells. This is your spending ceiling per category.
... B30: Yellow = enter data here. White/blue = automatic formulas, do not edit. Grey italics = example row, delete before use.

Sheet Budget Tracker
A1: Budget vs. Actual — by Category
A2: Category | B2: Budgeted Amount (AED) | C2: Actual Spend (AED) | D2: Variance (AED) | E2: % of Budget Used | F2: Notes / Justification
A3: Construction | C3: =SUMIFS('Expense Log'!$M$4:$M$201,'Expense Log'!$B$4:$B$201,A3) -> 0 | D3: =B3-C3 -> 0 | E3: =IFERROR(C3/B3,0) -> 0
A4: Machinery & Equipment | C4: =SUMIFS('Expense Log'!$M$4:$M$201,'Expense Log'!$B$4:$B$201,A4) -> 0 | D4: =B4-C4 -> 0 | E4: =IFERROR(C4/B4,0) -> 0
A5: Water | C5: =SUMIFS('Expense Log'!$M$4:$M$201,'Expense Log'!$B$4:$B$201,A5) -> 0 | D5: =B5-C5 -> 0 | E5: =IFERROR(C5/B5,0) -> 0
A6: Transportation | C6: =SUMIFS('Expense Log'!$M$4:$M$201,'Expense Log'!$B$4:$B$201,A6) -> 0 | D6: =B6-C6 -> 0 | E6: =IFERROR(C6/B6,0) -> 0
A7: Furniture & Fittings | C7: =SUMIFS('Expense Log'!$M$4:$M$201,'Expense Log'!$B$4:$B$201,A7) -> 0 | D7: =B7-C7 -> 0 | E7: =IFERROR(C7/B7,0) -> 0
A8: Utilities (Electricity/Gas) | C8: =SUMIFS('Expense Log'!$M$4:$M$201,'Expense Log'!$B$4:$B$201,A8) -> 0 | D8: =B8-C8 -> 0 | E8: =IFERROR(C8/B8,0) -> 0
A9: Permits & Licensing | C9: =SUMIFS('Expense Log'!$M$4:$M$201,'Expense Log'!$B$4:$B$201,A9) -> 0 | D9: =B9-C9 -> 0 | E9: =IFERROR(C9/B9,0) -> 0
A10: Labor / Contractor Fees | C10: =SUMIFS('Expense Log'!$M$4:$M$201,'Expense Log'!$B$4:$B$201,A10) -> 0 | D10: =B10-C10 -> 0 | E10: =IFERROR(C10/B10,0) -> 0
A11: Raw Materials & Supplies | C11: =SUMIFS('Expense Log'!$M$4:$M$201,'Expense Log'!$B$4:$B$201,A11) -> 0 | D11: =B11-C11 -> 0 | E11: =IFERROR(C11/B11,0) -> 0
A12: Marketing & Branding | C12: =SUMIFS('Expense Log'!$M$4:$M$201,'Expense Log'!$B$4:$B$201,A12) -> 0 | D12: =B12-C12 -> 0 | E12: =IFERROR(C12/B12,0) -> 0
A13: Contingency | C13: =SUMIFS('Expense Log'!$M$4:$M$201,'Expense Log'!$B$4:$B$201,A13) -> 0 | D13: =B13-C13 -> 0 | E13: =IFERROR(C13/B13,0) -> 0
A14: Miscellaneous | C14: =SUMIFS('Expense Log'!$M$4:$M$201,'Expense Log'!$B$4:$B$201,A14) -> 0 | D14: =B14-C14 -> 0 | E14: =IFERROR(C14/B14,0) -> 0
A15: TOTAL | B15: =SUM(B3:B14) -> 0 | C15: =SUM(C3:C14) -> 0 | D15: =SUM(D3:D14) -> 0 | E15: =IFERROR(C15/B15,0) -> 0
A17: Yellow cells = enter budget & notes. Actual, Variance, % Used calculate automatically from the Expense Log.

Sheet Expense Log
A1: Expense Log — All Transactions
A2: Date | B2: Category | C2: Sub-category / Item | D2: Description | E2: Vendor / Supplier | F2: Invoice / Receipt No. | G2: Payment Method | H2: Payment Status | I2: Currency | J2: Amount (Excl. Tax) | K2: VAT/Tax % | L2: VAT/Tax Amount | M2: Total Amount | N2: Approved By | O2: Project Phase | P2: Notes
A3: 2026-01-15 | B3: Construction | C3: Foundation & block work | D3: Phase 1 foundation and block work | E3: Al Noor Contracting | F3: INV-0001 | G3: Bank Transfer | H3: Paid | I3: AED | J3: 15000 | K3: 0.05 | L3: =J3*K3 -> 750 | M3: =J3+L3 -> 15750 | N3: K. Abolaji | O3: Construction | P3: Example row — delete before use
L4: =IF(J4="","",J4*K4) | M4: =IF(J4="","",J4+L4)
L5: =IF(J5="","",J5*K5) | M5: =IF(J5="","",J5+L5)
L6: =IF(J6="","",J6*K6) | M6: =IF(J6="","",J6+L6)
L7: =IF(J7="","",J7*K7) | M7: =IF(J7="","",J7+L7)
L8: =IF(J8="","",J8*K8) | M8: =IF(J8="","",J8+L8)
L9: =IF(J9="","",J9*K9) | M9: =IF(J9="","",J9+L9)
L10: =IF(J10="","",J10*K10) | M10: =IF(J10="","",J10+L10)
L11: =IF(J11="","",J11*K11) | M11: =IF(J11="","",J11+L11)
L12: =IF(J12="","",J12*K12) | M12: =IF(J12="","",J12+L12)
L13: =IF(J13="","",J13*K13) | M13: =IF(J13="","",J13+L13)
L14: =IF(J14="","",J14*K14) | M14: =IF(J14="","",J14+L14)
L15: =IF(J15="","",J15*K15) | M15: =IF(J15="","",J15+L15)
... L201: =IF(J201="","",J201*K201) | M201: =IF(J201="","",J201+L201)
I203: TOTAL | J203: =SUM(J4:J201) -> 0 | L203: =SUM(L4:L201) -> 0 | M203: =SUM(M4:M201) -> 0
A205: Legend: Yellow cells = enter your data. VAT/Tax Amount & Total Amount calculate automatically. Row 3 is an example — delete before use.

Sheet Dashboard
B2: SUBLA TEA — PROJECT EXPENSE DASHBOARD
B4: Total Budget (AED) | D4: Total Spent (AED) | F4: Remaining Budget (AED) | H4: % of Budget Used
B5: ='Budget Tracker'!B15 -> 0 | D5: ='Budget Tracker'!C15 -> 0 | F5: ='Budget Tracker'!D15 -> 0 | H5: ='Budget Tracker'!E15 -> 0
B9: Spend by Category | E9: Spend by Payment Status
B10: Category | C10: Actual (AED) | E10: Status | F10: Amount (AED)
B11: ='Budget Tracker'!A3 -> Construction | C11: ='Budget Tracker'!C3 -> 0 | E11: Paid | F11: =SUMIFS('Expense Log'!$M$4:$M$201,'Expense Log'!$H$4:$H$201,E11) -> 0
B12: ='Budget Tracker'!A4 -> Machinery & Equipment | C12: ='Budget Tracker'!C4 -> 0 | E12: Pending | F12: =SUMIFS('Expense Log'!$M$4:$M$201,'Expense Log'!$H$4:$H$201,E12) -> 0
B13: ='Budget Tracker'!A5 -> Water | C13: ='Budget Tracker'!C5 -> 0 | E13: Partially Paid | F13: =SUMIFS('Expense Log'!$M$4:$M$201,'Expense Log'!$H$4:$H$201,E13) -> 0
B14: ='Budget Tracker'!A6 -> Transportation | C14: ='Budget Tracker'!C6 -> 0 | E14: Overdue | F14: =SUMIFS('Expense Log'!$M$4:$M$201,'Expense Log'!$H$4:$H$201,E14) -> 0
B15: ='Budget Tracker'!A7 -> Furniture & Fittings | C15: ='Budget Tracker'!C7 -> 0
B16: ='Budget Tracker'!A8 -> Utilities (Electricity/Gas) | C16: ='Budget Tracker'!C8 -> 0
B17: ='Budget Tracker'!A9 -> Permits & Licensing | C17: ='Budget Tracker'!C9 -> 0
B18: ='Budget Tracker'!A10 -> Labor / Contractor Fees | C18: ='Budget Tracker'!C10 -> 0
B19: ='Budget Tracker'!A11 -> Raw Materials & Supplies | C19: ='Budget Tracker'!C11 -> 0
B20: ='Budget Tracker'!A12 -> Marketing & Branding | C20: ='Budget Tracker'!C12 -> 0
B21: ='Budget Tracker'!A13 -> Contingency | C21: ='Budget Tracker'!C13 -> 0
B22: ='Budget Tracker'!A14 -> Miscellaneous | C22: ='Budget Tracker'!C14 -> 0
B42: All figures on this sheet update automatically. Do not edit — manage data in Budget Tracker and Expense Log.

Sheet Vendor Directory
A1: Vendor & Contractor Directory
A2: Vendor / Supplier | B2: Category | C2: Contact Person | D2: Phone | E2: Email | F2: Trade License No. | G2: Notes
